<?xml version="1.0" encoding="utf-8" standalone="yes"?><GraphicsDesignerTextRefs><Actualisation DateTime="26.05.2015 13:47:54" /><TextRef ID="14" UsedPlace="@page_arhives.pdl-&gt;Control1" ObjectType="CCAxAlarmControl.AxAlarmControl.1" /><TextRef ID="15" UsedPlace="@page_arhives.pdl-&gt;Control1" ObjectType="CCAxAlarmControl.AxAlarmControl.1" /><TextRef ID="16" UsedPlace="@page_arhives.pdl-&gt;Control1" ObjectType="CCAxAlarmControl.AxAlarmControl.1" /><TextRef ID="17" UsedPlace="@page_arhives.pdl-&gt;Control1" ObjectType="CCAxAlarmControl.AxAlarmControl.1" /><TextRef ID="18" UsedPlace="@page_arhives.pdl-&gt;Control1" ObjectType="CCAxAlarmControl.AxAlarmControl.1" /><TextRef ID="19" UsedPlace="@page_arhives.pdl-&gt;Control1" ObjectType="CCAxAlarmControl.AxAlarmControl.1" /><TextRef ID="20" UsedPlace="@page_arhives.pdl-&gt;Control1" ObjectType="CCAxAlarmControl.AxAlarmControl.1" /><TextRef ID="21" UsedPlace="@page_arhives.pdl-&gt;Control1" ObjectType="CCAxAlarmControl.AxAlarmControl.1" /><TextRef ID="22" UsedPlace="@page_arhives.pdl-&gt;Control1" ObjectType="CCAxAlarmControl.AxAlarmControl.1" /><TextRef ID="23" UsedPlace="@page_arhives.pdl-&gt;Control1" ObjectType="CCAxAlarmControl.AxAlarmControl.1" /><TextRef ID="24" UsedPlace="@page_arhives.pdl-&gt;Control1" ObjectType="CCAxAlarmControl.AxAlarmControl.1" /><TextRef ID="26" UsedPlace="@page_arhives.pdl-&gt;Control1" ObjectType="CCAxAlarmControl.AxAlarmControl.1" /><TextRef ID="27" UsedPlace="@page_arhives.pdl-&gt;Control1" ObjectType="CCAxAlarmControl.AxAlarmControl.1" /><TextRef ID="28" UsedPlace="@page_arhives.pdl-&gt;Control1" ObjectType="CCAxAlarmControl.AxAlarmControl.1" /><TextRef ID="29" UsedPlace="@page_arhives.pdl-&gt;Control1" ObjectType="CCAxAlarmControl.AxAlarmControl.1" /><TextRef ID="30" UsedPlace="@page_arhives.pdl-&gt;Control1" ObjectType="CCAxAlarmControl.AxAlarmControl.1" /><TextRef ID="31" UsedPlace="@page_arhives.pdl-&gt;Control1" ObjectType="CCAxAlarmControl.AxAlarmControl.1" /><TextRef ID="32" UsedPlace="@page_arhives.pdl-&gt;Control1" ObjectType="CCAxAlarmControl.AxAlarmControl.1" /><TextRef ID="33" UsedPlace="@page_arhives.pdl-&gt;Control1" ObjectType="CCAxAlarmControl.AxAlarmControl.1" /><TextRef ID="34" UsedPlace="@page_arhives.pdl-&gt;Control1" ObjectType="CCAxAlarmControl.AxAlarmControl.1" /><TextRef ID="35" UsedPlace="@page_arhives.pdl-&gt;Control1" ObjectType="CCAxAlarmControl.AxAlarmControl.1" /><TextRef ID="36" UsedPlace="@page_arhives.pdl-&gt;Control1" ObjectType="CCAxAlarmControl.AxAlarmControl.1" /><TextRef ID="37" UsedPlace="@page_arhives.pdl-&gt;Control1" ObjectType="CCAxAlarmControl.AxAlarmControl.1" /><TextRef ID="38" UsedPlace="@page_arhives.pdl-&gt;Control1" ObjectType="CCAxAlarmControl.AxAlarmControl.1" /><TextRef ID="39" UsedPlace="@page_arhives.pdl-&gt;Control1" ObjectType="CCAxAlarmControl.AxAlarmControl.1" /><TextRef ID="40" UsedPlace="@page_arhives.pdl-&gt;Control1" ObjectType="CCAxAlarmControl.AxAlarmControl.1" /><TextRef ID="41" UsedPlace="@page_arhives.pdl-&gt;Control1" ObjectType="CCAxAlarmControl.AxAlarmControl.1" /><TextRef ID="42" UsedPlace="@page_arhives.pdl-&gt;Control1" ObjectType="CCAxAlarmControl.AxAlarmControl.1" /><TextRef ID="43" UsedPlace="@page_arhives.pdl-&gt;Control1" ObjectType="CCAxAlarmControl.AxAlarmControl.1" /><TextRef ID="44" UsedPlace="@page_arhives.pdl-&gt;Control1" ObjectType="CCAxAlarmControl.AxAlarmControl.1" /><TextRef ID="45" UsedPlace="@page_arhives.pdl-&gt;Control1" ObjectType="CCAxAlarmControl.AxAlarmControl.1" /><TextRef ID="46" UsedPlace="@page_arhives.pdl-&gt;Control1" ObjectType="CCAxAlarmControl.AxAlarmControl.1" /><TextRef ID="47" UsedPlace="@page_arhives.pdl-&gt;Control1" ObjectType="CCAxAlarmControl.AxAlarmControl.1" /><TextRef ID="48" UsedPlace="@page_arhives.pdl-&gt;Control1" ObjectType="CCAxAlarmControl.AxAlarmControl.1" /><TextRef ID="49" UsedPlace="@page_arhives.pdl-&gt;Control1" ObjectType="CCAxAlarmControl.AxAlarmControl.1" /><TextRef ID="50" UsedPlace="@page_arhives.pdl-&gt;Control1" ObjectType="CCAxAlarmControl.AxAlarmControl.1" /><TextRef ID="51" UsedPlace="@page_arhives.pdl-&gt;Control1" ObjectType="CCAxAlarmControl.AxAlarmControl.1" /><TextRef ID="52" UsedPlace="@page_arhives.pdl-&gt;Control1" ObjectType="CCAxAlarmControl.AxAlarmControl.1" /><TextRef ID="53" UsedPlace="@page_arhives.pdl-&gt;Control1" ObjectType="CCAxAlarmControl.AxAlarmControl.1" /><TextRef ID="3297" UsedPlace="@page_arhives_alarms.pdl-&gt;Control1" ObjectType="CCAxAlarmControl.AxAlarmControl.1" /><TextRef ID="80" UsedPlace="@page_GraCS_fresh.pdl-&gt;Control1" ObjectType="CCAxAlarmControl.AxAlarmControl.1" /></GraphicsDesignerTextRefs>